build/lib/scipplan/__init__.py
build/lib/scipplan/config.py
build/lib/scipplan/helpers.py
build/lib/scipplan/parse_model.py
build/lib/scipplan/plan_model.py
build/lib/scipplan/scipplan.py
build/lib/scipplan/variables.py
build/lib/scipplan/zero_crossing.py
scipplan/__init__.py
scipplan/config.py
scipplan/helpers.py
scipplan/parse_model.py
scipplan/plan_model.py
scipplan/scipplan.py
scipplan/variables.py
scipplan/zero_crossing.py
scipplan/translation/odes_navigation_1.txt
scipplan/translation/odes_navigation_2.txt
scipplan/translation/odes_navigation_3.txt
scipplan/translation/solutions_navigation_1.txt
scipplan/translation/solutions_navigation_2.txt
scipplan/translation/solutions_navigation_3.txt
scipplan-0.2.2a0.dist-info/LICENSE
scipplan-0.2.2a0.dist-info/METADATA
scipplan-0.2.2a0.dist-info/WHEEL
scipplan-0.2.2a0.dist-info/entry_points.txt
scipplan-0.2.2a0.dist-info/top_level.txt
scipplan-0.2.2a0.dist-info/RECORD
