Metadata-Version: 2.1
Name: scipplan
Version: 0.2.2a0
Summary: Metric Hybrid Factored Planning in Nonlinear Domains with Constraint Generation in Python.
Author: Ari Gestetner, Buser Say
Author-email: ari.gestetner@monash.edu, buser.say@monash.edu
License: MIT License
Keywords: scip,automated planner
Classifier: Development Status :: 3 - Alpha
Classifier: Environment :: Console
Classifier: Intended Audience :: Science/Research
Classifier: License :: OSI Approved :: MIT License
Classifier: Natural Language :: English
Classifier: Operating System :: OS Independent
Classifier: Programming Language :: Python :: 3
Classifier: Topic :: Scientific/Engineering :: Artificial Intelligence
License-File: LICENSE
Requires-Dist: PySCIPOpt==5.2.1
Requires-Dist: sympy==1.13.3
